pythagora/__init__.py
pythagora/agents.py
pythagora/controls.py
pythagora/experiments.py
pythagora/generate.py
pythagora/groups.py
pythagora/logger.py
pythagora/market.py
pythagora/scalefree.py
pythagora/smallworld.py
pythagora-1.1.6.dist-info/LICENSE.txt
pythagora-1.1.6.dist-info/METADATA
pythagora-1.1.6.dist-info/WHEEL
pythagora-1.1.6.dist-info/top_level.txt
pythagora-1.1.6.dist-info/RECORD
