Metadata-Version: 2.1
Name: pythagora
Version: 1.1.6
Summary: A Python Package for Modeling the Impact of Social Networks on Market Outcomes
Author-email: "Sarah T. Wilker" <swilker@alumni.stanford.edu>, "Annie K. Lamar" <aklamar@ucsb.edu>
Project-URL: Source, https://github.com/stwilker/pythagora
Project-URL: Docs, https://stwilker.github.io/pythagora
Classifier: Programming Language :: Python :: 3
Classifier: License :: Other/Proprietary License
Classifier: Operating System :: OS Independent
Requires-Python: >=3.8
License-File: LICENSE.txt
